{
  "Profiles": [
    {
      "Name": "stainless",
      "Guid": "stainless-profile-001",
      "Background Color (Light)": {
        "Red Component": 0.89,
        "Green Component": 0.95,
        "Blue Component": 0.99
      },
      "Background Color (Dark)": {
        "Red Component": 0.12,
        "Green Component": 0.23,
        "Blue Component": 0.37
      },
      "Foreground Color (Light)": {
        "Red Component": 0.0,
        "Green Component": 0.0,
        "Blue Component": 0.0
      },
      "Foreground Color (Dark)": {
        "Red Component": 0.9,
        "Green Component": 0.9,
        "Blue Component": 0.9
      },
      "Badge Text": "stainless",
      "Use Bold Font": true,
      "Use Bright Bold": true,
      "Use Italic Font": false,
      "Transparency": 0,
      "Blur": false
    },
    {
      "Name": "nsheaps",
      "Guid": "nsheaps-profile-001",
      "Background Color (Light)": {
        "Red Component": 0.95,
        "Green Component": 0.9,
        "Blue Component": 0.96
      },
      "Background Color (Dark)": {
        "Red Component": 0.24,
        "Green Component": 0.16,
        "Blue Component": 0.28
      },
      "Foreground Color (Light)": {
        "Red Component": 0.0,
        "Green Component": 0.0,
        "Blue Component": 0.0
      },
      "Foreground Color (Dark)": {
        "Red Component": 0.9,
        "Green Component": 0.9,
        "Blue Component": 0.9
      },
      "Badge Text": "nsheaps",
      "Use Bold Font": true,
      "Use Bright Bold": true,
      "Use Italic Font": false,
      "Transparency": 0,
      "Blur": false
    }
  ]
}
